{"id":"t9bw11yxt81pszb8bk1tk9h","title":"Moving Least Square","desc":"","updated":1648698049120,"created":1648698049120,"custom":{},"fname":"optimization.least-square.moving-least-square","type":"note","vault":{"fsPath":"vault"},"contentHash":"52bcd957fc4f86ef3fa245b68ec17958","links":[{"type":"wiki","from":{"fname":"optimization.least-square.moving-least-square","id":"t9bw11yxt81pszb8bk1tk9h","vaultName":"vault"},"value":"probability.parameter-estimation.maximum-likelihood-estimation-mle","alias":"Polynomial basis","position":{"start":{"line":4,"column":74,"offset":190},"end":{"line":4,"column":178,"offset":294},"indent":[]},"xvault":false,"sameFile":false,"to":{"fname":"probability.parameter-estimation.maximum-likelihood-estimation-mle","anchorHeader":"polynomial-basis"}},{"type":"wiki","from":{"fname":"optimization.least-square.moving-least-square","id":"t9bw11yxt81pszb8bk1tk9h","vaultName":"vault"},"value":"linear-algebra.feature-extraction.principle-component-analysis","alias":"Kernel Trick","position":{"start":{"line":56,"column":12,"offset":2271},"end":{"line":56,"column":104,"offset":2363},"indent":[]},"xvault":false,"sameFile":false,"to":{"fname":"linear-algebra.feature-extraction.principle-component-analysis","anchorHeader":"kernel-trick"}},{"from":{"fname":"geometry.signed-distance-function","vaultName":"vault"},"type":"backlink","position":{"start":{"line":95,"column":10,"offset":3857},"end":{"line":95,"column":59,"offset":3906},"indent":[]},"value":"optimization.least-square.moving-least-square","alias":"optimization.least-square.moving-least-square"}],"anchors":{"derivatives-computation":{"type":"header","text":"Derivatives computation","value":"derivatives-computation","line":22,"column":0,"depth":2},"wendland-function":{"type":"header","text":"Wendland function","value":"wendland-function","line":39,"column":0,"depth":2},"radial-basis-function":{"type":"header","text":"Radial Basis function","value":"radial-basis-function","line":61,"column":0,"depth":3},"^2":{"type":"block","value":"2","line":13,"column":130}},"children":[],"parent":"0901aqnyeeuh145frdq3auv","data":{}}
