{"id":"x4oiJfDX92iPcvHw7527C","title":"Maximum a Posterior Estimate (MAP)","desc":"","updated":1641631754946,"created":1641629287028,"custom":{},"fname":"probability.parameter-estimation.maximum-a-posterior-estimate-map","type":"note","vault":{"fsPath":"vault"},"contentHash":"651e61c995656222bb15e15c8f1af0fe","links":[{"type":"wiki","from":{"fname":"probability.parameter-estimation.maximum-a-posterior-estimate-map","id":"x4oiJfDX92iPcvHw7527C","vaultName":"vault"},"value":"probability.parameter-estimation.maximum-likelihood-estimation-mle","alias":"MLE with Regularization","position":{"start":{"line":22,"column":21,"offset":714},"end":{"line":22,"column":130,"offset":823},"indent":[]},"xvault":false,"sameFile":false,"to":{"fname":"probability.parameter-estimation.maximum-likelihood-estimation-mle","anchorHeader":"regularization"}}],"anchors":{"^2":{"type":"block","value":"2","line":25,"column":95}},"children":[],"parent":"fHMmzepyNqegNyO1rPHZJ","data":{}}
